[
  {
    "trial_id": "NCT03301350",
    "trial_title": "Neoadjuvant Carbo/Paclitaxel Followed by Doxorubicin/Cyclophosphamide in Breast Cancer",
    "mcode_elements": {
      "ClinicalTrial": {
        "id": "NCT03301350",
        "title": "Neoadjuvant Carbo/Paclitaxel Followed by Doxorubicin/Cyclophosphamide in Breast Cancer",
        "phase": "Phase 2",
        "status": "COMPLETED",
        "startDate": "2017-11-07",
        "completionDate": "2022-02-07",
        "sponsor": "Academic Medical Center",
        "codedAs": {
          "system": "http://clinicaltrials.gov",
          "code": "NCT03301350",
          "display": "Neoadjuvant Carbo/Paclitaxel Followed by Doxorubicin/Cyclophosphamide in Breast Cancer"
        }
      },
      "CancerCondition": {
        "display": "Triple Negative Breast Cancer",
        "code": {
          "system": "http://snomed.info/sct",
          "code": "420120006",
          "display": "Triple negative malignant neoplasm of breast"
        },
        "interpretation": "Confirmed"
      },
      "EligibilityCriteria": {
        "inclusion": [
          {
            "CancerCondition": {
              "display": "Triple Negative Breast Cancer",
              "code": {
                "system": "http://snomed.info/sct",
                "code": "420120006",
                "display": "Triple negative malignant neoplasm of breast"
              }
            }
          },
          {
            "ECOGPerformanceStatus": {
              "code": {
                "system": "http://loinc.org",
                "code": "LA9622-7",
                "display": "ECOG performance status 0"
              },
              "interpretation": "ECOG 0-1"
            }
          }
        ],
        "exclusion": [
          {
            "PriorTreatment": {
              "display": "Prior chemotherapy for breast cancer",
              "code": {
                "system": "http://snomed.info/sct",
                "code": "371147001",
                "display": "Chemotherapy regimen"
              }
            }
          }
        ]
      },
      "CancerRelatedMedicationStatement": [
        {
          "medicationCodeableConcept": {
            "coding": [
              {
                "system": "http://www.nlm.nih.gov/research/umls/rxnorm",
                "code": "194000",
                "display": "Carboplatin"
              }
            ]
          },
          "dosage": {
            "doseAndRate": {
              "doseQuantity": {
                "value": 2,
                "unit": "AUC",
                "system": "http://unitsofmeasure.org",
                "code": "{AUC}"
              }
            },
            "route": {
              "coding": [
                {
                  "system": "http://snomed.info/sct",
                  "code": "47625008",
                  "display": "Intravenous route"
                }
              ]
            }
          },
          "effectivePeriod": {
            "start": "2017-11-07",
            "end": "2018-02-07"
          }
        },
        {
          "medicationCodeableConcept": {
            "coding": [
              {
                "system": "http://www.nlm.nih.gov/research/umls/rxnorm",
                "code": "56946",
                "display": "Paclitaxel"
              }
            ]
          },
          "dosage": {
            "doseAndRate": {
              "doseQuantity": {
                "value": 80,
                "unit": "mg/m2",
                "system": "http://unitsofmeasure.org",
                "code": "mg/m2"
              }
            },
            "route": {
              "coding": [
                {
                  "system": "http://snomed.info/sct",
                  "code": "47625008",
                  "display": "Intravenous route"
                }
              ]
            }
          },
          "effectivePeriod": {
            "start": "2017-11-07",
            "end": "2018-02-07"
          }
        }
      ],
      "StudyDesign": {
        "studyType": "Interventional",
        "phase": "Phase 2",
        "allocation": "Non-Randomized",
        "interventionModel": "Single Group Assignment",
        "primaryPurpose": "Treatment",
        "masking": "None"
      }
    }
  },
  {
    "trial_id": "NCT01367418",
    "trial_title": "Effects of Anesthetic Technique on Immune and Inflammatory Systems Following Radical Prostatectomy",
    "mcode_elements": {
      "ClinicalTrial": {
        "id": "NCT01367418",
        "title": "Effects of Anesthetic Technique on Immune and Inflammatory Systems Following Radical Prostatectomy",
        "phase": "N/A",
        "status": "COMPLETED",
        "startDate": "2010-09",
        "completionDate": "2012-03",
        "sponsor": "University Hospital",
        "codedAs": {
          "system": "http://clinicaltrials.gov",
          "code": "NCT01367418",
          "display": "Effects of Anesthetic Technique on Immune and Inflammatory Systems Following Radical Prostatectomy"
        }
      },
      "CancerCondition": {
        "display": "Prostate Cancer",
        "code": {
          "system": "http://snomed.info/sct",
          "code": "254900004",
          "display": "Malignant neoplasm of prostate"
        },
        "interpretation": "Confirmed"
      },
      "EligibilityCriteria": {
        "inclusion": [
          {
            "CancerCondition": {
              "display": "Prostate Cancer",
              "code": {
                "system": "http://snomed.info/sct",
                "code": "254900004",
                "display": "Malignant neoplasm of prostate"
              }
            }
          },
          {
            "Procedure": {
              "display": "Radical Prostatectomy",
              "code": {
                "system": "http://snomed.info/sct",
                "code": "26294005",
                "display": "Radical prostatectomy"
              }
            }
          }
        ],
        "exclusion": []
      },
      "CancerRelatedSurgicalProcedure": [
        {
          "procedureCode": {
            "coding": [
              {
                "system": "http://snomed.info/sct",
                "code": "26294005",
                "display": "Radical prostatectomy"
              }
            ]
          },
          "status": "completed",
          "performedPeriod": {
            "start": "2010-09",
            "end": "2012-03"
          }
        }
      ],
      "StudyDesign": {
        "studyType": "Observational",
        "allocation": "Randomized",
        "interventionModel": "Parallel Assignment",
        "primaryPurpose": "Basic Science",
        "masking": "Single"
      },
      "ResearchSubject": {
        "studyArm": [
          {
            "name": "Thoracic Epidural Analgesia",
            "type": "Experimental"
          },
          {
            "name": "Patient Controlled Analgesia",
            "type": "Active Comparator"
          }
        ]
      }
    }
  }
]